apconfig/__init__.py
apconfig/utilities.py
apconfig-0.0.117.dist-info/METADATA
apconfig-0.0.117.dist-info/WHEEL
apconfig-0.0.117.dist-info/RECORD
