Metadata-Version: 2.1
Name: apconfig
Version: 0.0.117
Summary: 
Author: Makhosonke Morafo
Author-email: makhosonke@komokun.org
Requires-Python: >=3.9,<3.11
Classifier: Programming Language :: Python :: 3
Classifier: Programming Language :: Python :: 3.9
Classifier: Programming Language :: Python :: 3.10
Requires-Dist: requests (>=2.31.0,<3.0.0)
